sphinx_sqlite3fts/__init__.py
sphinx_sqlite3fts/builders.py
sphinx_sqlite3fts/cli.py
sphinx_sqlite3fts/events.py
sphinx_sqlite3fts/models.py
sphinx_sqlite3fts/services.py
sphinx_sqlite3fts/utils.py
sphinx_sqlite3fts/static/searchtools.js
sphinx_sqlite3fts-0.1.2.dist-info/entry_points.txt
sphinx_sqlite3fts-0.1.2.dist-info/LICENSE
sphinx_sqlite3fts-0.1.2.dist-info/WHEEL
sphinx_sqlite3fts-0.1.2.dist-info/METADATA
sphinx_sqlite3fts-0.1.2.dist-info/RECORD
