Metadata-Version: 2.1
Name: sphinx-sqlite3fts
Version: 0.1.2
Summary: Sphinx document searcher using SQLite3.
Author-email: Kazuya Takei <myself@attakei.net>
Classifier: Development Status :: 4 - Beta
Classifier: Environment :: Console
Classifier: Environment :: Web Environment
Classifier: Framework :: Sphinx
Classifier: Framework :: Sphinx :: Extension
Classifier: Intended Audience :: Developers
Classifier: License :: OSI Approved :: Apache Software License
Classifier: Operating System :: OS Independent
Classifier: Programming Language :: Python
Classifier: Programming Language :: Python :: 3
Classifier: Programming Language :: Python :: 3 :: Only
Classifier: Programming Language :: Python :: 3.7
Classifier: Programming Language :: Python :: 3.8
Classifier: Programming Language :: Python :: 3.9
Classifier: Programming Language :: Python :: 3.10
Classifier: Programming Language :: Python :: 3.11
Classifier: Topic :: Documentation :: Sphinx
Classifier: Topic :: Internet :: WWW/HTTP :: Indexing/Search
Classifier: Topic :: Internet :: WWW/HTTP :: Site Management
Classifier: Topic :: Software Development
Classifier: Topic :: Software Development :: Documentation
Classifier: Topic :: Text Processing :: Markup :: HTML
Requires-Dist: docutils
Requires-Dist: peewee
Requires-Dist: Sphinx
Requires-Dist: Click ; extra == "cli"
Requires-Dist: furo ; extra == "docs"
Requires-Dist: sphinx-intl ; extra == "docs"
Requires-Dist: pytest ; extra == "test"
Project-URL: Documentation, https://sphinx-sqlite3fts.readthedocs.io/
Project-URL: Home, https://attakei-lab.github.io/sphinx-sqlite3fts
Project-URL: Repository, https://github.com/attakei-lab/sphinx-sqlite3fts
Provides-Extra: cli
Provides-Extra: docs
Provides-Extra: test
